mypackage/__init__.py
mypackage/matrix_dot.py
mypackage/ols.py
softwaretoolbc-0.2.dist-info/METADATA
softwaretoolbc-0.2.dist-info/WHEEL
softwaretoolbc-0.2.dist-info/top_level.txt
softwaretoolbc-0.2.dist-info/RECORD
