Metadata-Version: 2.1
Name: softwaretoolbc
Version: 0.2
Summary: Library written by Dennis Guo for Stefano
Home-page: UNKNOWN
Author: Dennis Guo
Author-email: guohq@bc.edu
License: MIT
Platform: UNKNOWN
Classifier: Programming Language :: Python :: 3
